protean/__init__.py
protean/__main__.py
protean/adapters/__init__.py
protean/adapters/broker/__init__.py
protean/adapters/broker/inline.py
protean/adapters/broker/redis.py
protean/adapters/broker/redis_pubsub.py
protean/adapters/cache/__init__.py
protean/adapters/cache/memory.py
protean/adapters/cache/redis.py
protean/adapters/email/__init__.py
protean/adapters/email/dummy.py
protean/adapters/email/sendgrid.py
protean/adapters/event_store/__init__.py
protean/adapters/event_store/memory.py
protean/adapters/event_store/message_db.py
protean/adapters/repository/__init__.py
protean/adapters/repository/elasticsearch.py
protean/adapters/repository/memory.py
protean/adapters/repository/sqlalchemy.py
protean/cli/__init__.py
protean/cli/docs.py
protean/cli/generate.py
protean/cli/new.py
protean/cli/server2.py
protean/cli/shell.py
protean/cli/test.py
protean/core/__init__.py
protean/core/aggregate.py
protean/core/application_service.py
protean/core/command.py
protean/core/command_handler.py
protean/core/database_model.py
protean/core/domain_service.py
protean/core/email.py
protean/core/entity.py
protean/core/event.py
protean/core/event_handler.py
protean/core/event_sourced_repository.py
protean/core/projection.py
protean/core/projector.py
protean/core/queryset.py
protean/core/repository.py
protean/core/subscriber.py
protean/core/unit_of_work.py
protean/core/value_object.py
protean/domain/__init__.py
protean/domain/config.py
protean/domain/context.py
protean/domain/helpers.py
protean/domain/registry.py
protean/exceptions.py
protean/fields/__init__.py
protean/fields/association.py
protean/fields/base.py
protean/fields/basic.py
protean/fields/embedded.py
protean/fields/mixins.py
protean/fields/validators.py
protean/port/__init__.py
protean/port/broker.py
protean/port/cache.py
protean/port/dao.py
protean/port/event_store.py
protean/port/provider.py
protean/server/__init__.py
protean/server/engine.py
protean/server/fastapi_server.py
protean/server/outbox_processor.py
protean-0.14.2.dist-info/LICENSE
protean-0.14.2.dist-info/METADATA
protean-0.14.2.dist-info/WHEEL
protean-0.14.2.dist-info/entry_points.txt
protean-0.14.2.dist-info/RECORD
