Metadata-Version: 2.3
Name: protean
Version: 0.14.2
Summary: Protean Application Framework
License: BSD 3-Clause
Keywords: ddd,domain-driven-design,clean-architecture,hexagonal-architecture,onion-architecture,microservices,python-framework,repository-pattern,cqrs,event-sourcing,aggregates,entities,value-objects,services,bounded-contexts,asynchronous,event-driven-architecture,cqrs-framework,event-sourcing-framework
Author: Subhash Bhushan C
Author-email: subhash@team8solutions.com
Requires-Python: >=3.11,<4.0
Classifier: Development Status :: 2 - Pre-Alpha
Classifier: Intended Audience :: Developers
Classifier: License :: OSI Approved :: BSD License
Classifier: License :: Other/Proprietary License
Classifier: Operating System :: OS Independent
Classifier: Programming Language :: Python
Classifier: Programming Language :: Python :: 3
Classifier: Programming Language :: Python :: 3.11
Classifier: Programming Language :: Python :: 3.12
Classifier: Programming Language :: Python :: 3.13
Classifier: Programming Language :: Python :: 3 :: Only
Classifier: Topic :: Software Development :: Libraries
Classifier: Topic :: Software Development :: Libraries :: Application Frameworks
Classifier: Topic :: Software Development :: Libraries :: Python Modules
Provides-Extra: elasticsearch
Provides-Extra: fastapi
Provides-Extra: flask
Provides-Extra: message-db
Provides-Extra: mssql
Provides-Extra: postgresql
Provides-Extra: redis
Provides-Extra: sendgrid
Provides-Extra: sqlite
Requires-Dist: bleach (>=4.1.0)
Requires-Dist: cffi (>=1.16.5)
Requires-Dist: copier (>=9.1.1,<10.0.0)
Requires-Dist: elasticsearch (>=7.17.9,<7.18.0) ; extra == "elasticsearch"
Requires-Dist: elasticsearch-dsl (>=7.4.1,<7.5.0) ; extra == "elasticsearch"
Requires-Dist: fastapi (>=0.110.0) ; extra == "fastapi"
Requires-Dist: flask (>=1.1.1) ; extra == "flask"
Requires-Dist: greenlet (>=3.0.3,<4.0.0)
Requires-Dist: inflection (>=0.5.1)
Requires-Dist: ipython (>=8.23,<10.0)
Requires-Dist: marshmallow (>=3.15.0)
Requires-Dist: message-db-py (>=0.2.0) ; extra == "message-db"
Requires-Dist: psycopg2 (>=2.9.9) ; extra == "postgresql"
Requires-Dist: pydantic-core (>=2.19.1,<3.0.0)
Requires-Dist: pyodbc (>=5.0.0) ; extra == "mssql"
Requires-Dist: python-dateutil (>=2.8.2)
Requires-Dist: redis (>=5.0.7,<6.5.0) ; extra == "redis"
Requires-Dist: sendgrid (>=6.1.3) ; extra == "sendgrid"
Requires-Dist: sqlalchemy (>=2.0.30,<2.1.0) ; extra == "postgresql" or extra == "sqlite" or extra == "mssql"
Requires-Dist: typer (>=0.12.3)
Requires-Dist: uvicorn (>=0.27.1) ; extra == "fastapi"
Requires-Dist: werkzeug (>=2.0.0)
Project-URL: Documentation, https://protean.readthedocs.io/en/latest/
Project-URL: Repository, https://github.com/proteanhq/protean
